{"field":["152","194","213","2226","2305","238","245","30","38","59","84","99"],"bracket":{"seeds":[{"team_id":"245","team_name":"Texas A&M Aggies","seed":1,"fpi":36.29},{"team_id":"194","team_name":"Ohio State Buckeyes","seed":2,"fpi":30.48},{"team_id":"99","team_name":"LSU Tigers","seed":3,"fpi":27.54},{"team_id":"84","team_name":"Indiana Hoosiers","seed":4,"fpi":22.17},{"team_id":"30","team_name":"USC Trojans","seed":5,"fpi":20.02},{"team_id":"2305","team_name":"Kansas Jayhawks","seed":6,"fpi":18.44},{"team_id":"59","team_name":"Georgia Tech Yellow Jackets","seed":7,"fpi":16.24},{"team_id":"238","team_name":"Vanderbilt Commodores","seed":8,"fpi":15.37},{"team_id":"213","team_name":"Penn State Nittany Lions","seed":9,"fpi":13.89},{"team_id":"38","team_name":"Colorado Buffaloes","seed":10,"fpi":13.68},{"team_id":"152","team_name":"NC State Wolfpack","seed":11,"fpi":9.59},{"team_id":"2226","team_name":"Florida Atlantic Owls","seed":12,"fpi":6.96}],"r1":[[5,12],[6,11],[7,10],[8,9]],"title_odds_by_team_id":{"245":47.11,"194":21.79,"99":18.04,"84":6.74,"30":2.95,"2305":1.74,"59":0.57,"238":0.42,"213":0.26,"38":0.25,"152":0.1,"2226":0.04}},"conf_champions":{"ACC":"59","American":"2226","Big 12":"38","Big Ten":"194","CUSA":"338","MAC":"195","Mountain West":"62","Pac-12":"278","SEC":"99","Sun Belt":"2653"},"conf_finalists":{"ACC":["152","59"],"American":["2426","2226"],"Big 12":["2305","38"],"Big Ten":["30","194"],"CUSA":["338","98"],"MAC":["195","2711"],"Mountain West":["2439","62"],"Pac-12":["278","328"],"SEC":["245","99"],"Sun Belt":["2653","2026"]}}