{"field":["2","2132","221","238","2393","245","25","2509","2579","264","30","84"],"bracket":{"seeds":[{"team_id":"84","team_name":"Indiana Hoosiers","seed":1,"fpi":40.0},{"team_id":"238","team_name":"Vanderbilt Commodores","seed":2,"fpi":35.22},{"team_id":"2","team_name":"Auburn Tigers","seed":3,"fpi":30.23},{"team_id":"30","team_name":"USC Trojans","seed":4,"fpi":29.41},{"team_id":"264","team_name":"Washington Huskies","seed":5,"fpi":29.29},{"team_id":"221","team_name":"Pittsburgh Panthers","seed":6,"fpi":28.88},{"team_id":"245","team_name":"Texas A&M Aggies","seed":7,"fpi":27.48},{"team_id":"2132","team_name":"Cincinnati Bearcats","seed":8,"fpi":20.45},{"team_id":"2579","team_name":"South Carolina Gamecocks","seed":9,"fpi":20.36},{"team_id":"25","team_name":"California Golden Bears","seed":10,"fpi":20.13},{"team_id":"2509","team_name":"Purdue Boilermakers","seed":11,"fpi":11.47},{"team_id":"2393","team_name":"Middle Tennessee Blue Raiders","seed":12,"fpi":-8.69}],"r1":[[5,12],[6,11],[7,10],[8,9]],"title_odds_by_team_id":{"84":43.29,"238":20.3,"2":10.41,"30":8.34,"264":7.79,"221":6.08,"245":2.67,"2132":0.42,"2579":0.41,"25":0.28,"2509":0.02,"2393":0.0}},"conf_champions":{"ACC":"221","American":"249","Big 12":"2132","Big Ten":"2509","CUSA":"98","MAC":"2649","Mountain West":"62","Pac-12":"68","SEC":"245","Sun Belt":"6"},"conf_finalists":{"ACC":["221","2390"],"American":["249","218"],"Big 12":["2641","2132"],"Big Ten":["84","2509"],"CUSA":["2393","98"],"MAC":["2649","195"],"Mountain West":["2751","62"],"Pac-12":["68","21"],"SEC":["238","245"],"Sun Belt":["324","6"]}}