{"field":["2306","2390","245","2483","252","254","2567","2641","275","349","57","77"],"bracket":{"seeds":[{"team_id":"2483","team_name":"Oregon Ducks","seed":1,"fpi":40.0},{"team_id":"245","team_name":"Texas A&M Aggies","seed":2,"fpi":34.71},{"team_id":"57","team_name":"Florida Gators","seed":3,"fpi":33.08},{"team_id":"252","team_name":"BYU Cougars","seed":4,"fpi":23.52},{"team_id":"275","team_name":"Wisconsin Badgers","seed":5,"fpi":23.4},{"team_id":"2641","team_name":"Texas Tech Red Raiders","seed":6,"fpi":22.31},{"team_id":"2567","team_name":"SMU Mustangs","seed":7,"fpi":20.81},{"team_id":"2306","team_name":"Kansas State Wildcats","seed":8,"fpi":17.59},{"team_id":"254","team_name":"Utah Utes","seed":9,"fpi":17.5},{"team_id":"349","team_name":"Army Black Knights","seed":10,"fpi":17.07},{"team_id":"77","team_name":"Northwestern Wildcats","seed":11,"fpi":11.51},{"team_id":"2390","team_name":"Miami Hurricanes","seed":12,"fpi":9.89}],"r1":[[5,12],[6,11],[7,10],[8,9]],"title_odds_by_team_id":{"2483":45.31,"245":21.77,"57":22.88,"252":4.04,"275":2.79,"2641":1.78,"2567":0.65,"2306":0.26,"254":0.25,"349":0.19,"77":0.05,"2390":0.04}},"conf_champions":{"ACC":"2390","American":"349","Big 12":"252","Big Ten":"2483","CUSA":"2229","MAC":"2649","Mountain West":"2459","Pac-12":"68","SEC":"57","Sun Belt":"309"},"conf_finalists":{"ACC":["2567","2390"],"American":["349","2426"],"Big 12":["254","252"],"Big Ten":["275","2483"],"CUSA":["98","2229"],"MAC":["2649","113"],"Mountain West":["23","2459"],"Pac-12":["36","68"],"SEC":["57","245"],"Sun Belt":["309","2032"]}}