{"field":["120","142","2305","2306","2390","2483","258","2633","66","68","84","97"],"bracket":{"seeds":[{"team_id":"2483","team_name":"Oregon Ducks","seed":1,"fpi":40.0},{"team_id":"142","team_name":"Missouri Tigers","seed":2,"fpi":34.05},{"team_id":"84","team_name":"Indiana Hoosiers","seed":3,"fpi":29.37},{"team_id":"68","team_name":"Boise State Broncos","seed":4,"fpi":27.0},{"team_id":"2390","team_name":"Miami Hurricanes","seed":5,"fpi":25.23},{"team_id":"2633","team_name":"Tennessee Volunteers","seed":6,"fpi":23.52},{"team_id":"97","team_name":"Louisville Cardinals","seed":7,"fpi":19.81},{"team_id":"66","team_name":"Iowa State Cyclones","seed":8,"fpi":13.71},{"team_id":"120","team_name":"Maryland Terrapins","seed":9,"fpi":13.04},{"team_id":"2306","team_name":"Kansas State Wildcats","seed":10,"fpi":11.41},{"team_id":"258","team_name":"Virginia Cavaliers","seed":11,"fpi":10.63},{"team_id":"2305","team_name":"Kansas Jayhawks","seed":12,"fpi":4.71}],"r1":[[5,12],[6,11],[7,10],[8,9]],"title_odds_by_team_id":{"2483":50.06,"142":21.69,"84":12.65,"68":7.76,"2390":4.32,"2633":2.56,"97":0.68,"66":0.12,"120":0.09,"2306":0.04,"258":0.04,"2305":0.0}},"conf_champions":{"ACC":"97","American":"2655","Big 12":"2305","Big Ten":"2483","CUSA":"2335","MAC":"193","Mountain West":"2439","Pac-12":"68","SEC":"142","Sun Belt":"256"},"conf_finalists":{"ACC":["97","258"],"American":["151","2655"],"Big 12":["2305","2306"],"Big Ten":["2483","84"],"CUSA":["55","2335"],"MAC":["193","2084"],"Mountain West":["2439","2005"],"Pac-12":["68","326"],"SEC":["2633","142"],"Sun Belt":["276","256"]}}