{"field":["120","213","2390","2483","251","2641","265","333","59","84","87","97"],"bracket":{"seeds":[{"team_id":"97","team_name":"Louisville Cardinals","seed":1,"fpi":38.31},{"team_id":"59","team_name":"Georgia Tech Yellow Jackets","seed":2,"fpi":33.51},{"team_id":"87","team_name":"Notre Dame Fighting Irish","seed":3,"fpi":31.94},{"team_id":"251","team_name":"Texas Longhorns","seed":4,"fpi":27.25},{"team_id":"2390","team_name":"Miami Hurricanes","seed":5,"fpi":25.64},{"team_id":"84","team_name":"Indiana Hoosiers","seed":6,"fpi":24.45},{"team_id":"2483","team_name":"Oregon Ducks","seed":7,"fpi":19.17},{"team_id":"2641","team_name":"Texas Tech Red Raiders","seed":8,"fpi":16.57},{"team_id":"120","team_name":"Maryland Terrapins","seed":9,"fpi":15.63},{"team_id":"333","team_name":"Alabama Crimson Tide","seed":10,"fpi":14.45},{"team_id":"213","team_name":"Penn State Nittany Lions","seed":11,"fpi":12.75},{"team_id":"265","team_name":"Washington State Cougars","seed":12,"fpi":4.84}],"r1":[[5,12],[6,11],[7,10],[8,9]],"title_odds_by_team_id":{"97":42.92,"59":21.88,"87":18.76,"251":7.88,"2390":4.56,"84":2.8,"2483":0.58,"2641":0.26,"120":0.19,"333":0.12,"213":0.06,"265":0.0}},"conf_champions":{"ACC":"97","American":"235","Big 12":"2641","Big Ten":"120","CUSA":"2623","MAC":"2649","Mountain West":"2005","Pac-12":"328","SEC":"333","Sun Belt":"256"},"conf_finalists":{"ACC":["97","2390"],"American":["235","2636"],"Big 12":["252","2641"],"Big Ten":["120","2483"],"CUSA":["2623","55"],"MAC":["2649","193"],"Mountain West":["167","2005"],"Pac-12":["265","328"],"SEC":["251","333"],"Sun Belt":["256","2026"]}}